<Specialities xmlns=""><specialities><specialities><name>CS</name><facultyName>KSaN</facultyName><places>4</places><code>535</code><requiredSubjects><requiredSubjects>Russian</requiredSubjects><requiredSubjects>Math</requiredSubjects><requiredSubjects>English</requiredSubjects></requiredSubjects><enrolled><enrolled><id>16</id><personalData><name>1001</name><surname>1001</surname><patronymic>1001</patronymic></personalData><specialtyName>CS</specialtyName><ticketNo>95350001</ticketNo><totalMark>372</totalMark><specialityName>CS</specialityName></enrolled><enrolled><id>18</id><personalData><name>1002</name><surname>1002</surname><patronymic>1002</patronymic></personalData><specialtyName>CS</specialtyName><ticketNo>95350002</ticketNo><totalMark>369</totalMark><specialityName>CS</specialityName></enrolled><enrolled><id>20</id><personalData><name>1003</name><surname>1003</surname><patronymic>1003</patronymic></personalData><specialtyName>CS</specialtyName><ticketNo>95350003</ticketNo><totalMark>366</totalMark><specialityName>CS</specialityName></enrolled><enrolled><id>22</id><personalData><name>1004</name><surname>1004</surname><patronymic>1004</patronymic></personalData><specialtyName>CS</specialtyName><ticketNo>95350004</ticketNo><totalMark>363</totalMark><specialityName>CS</specialityName></enrolled></enrolled><maxId>0</maxId></specialities><specialities><name>QQQ</name><facultyName>KSaN</facultyName><places>4</places><code>111</code><requiredSubjects><requiredSubjects>Russian</requiredSubjects><requiredSubjects>Physics</requiredSubjects><requiredSubjects>Math</requiredSubjects></requiredSubjects><enrolled></enrolled><maxId>0</maxId></specialities><specialities><name>SWIT</name><facultyName>KSaN</facultyName><places>3</places><code>510</code><requiredSubjects><requiredSubjects>Russian</requiredSubjects><requiredSubjects>Physics</requiredSubjects><requiredSubjects>Math</requiredSubjects></requiredSubjects><enrolled><enrolled><id>14</id><personalData><name>Kek</name><surname>Lol</surname><patronymic>Cheburek</patronymic></personalData><specialtyName>SWIT</specialtyName><ticketNo>95100003</ticketNo><totalMark>400</totalMark><specialityName>SWIT</specialityName></enrolled><enrolled><id>15</id><personalData><name>1</name><surname>1</surname><patronymic>1</patronymic></personalData><specialtyName>SWIT</specialtyName><ticketNo>95100001</ticketNo><totalMark>372</totalMark><specialityName>SWIT</specialityName></enrolled><enrolled><id>17</id><personalData><name>2</name><surname>2</surname><patronymic>2</patronymic></personalData><specialtyName>SWIT</specialtyName><ticketNo>95100002</ticketNo><totalMark>369</totalMark><specialityName>SWIT</specialityName></enrolled></enrolled><maxId>0</maxId></specialities></specialities><maxId>0</maxId></Specialities>